{
    "address1": "Royal Bank Plaza",
    "address2": "200 Bay Street",
    "city": "Toronto",
    "state": "ON",
    "zip": "M5J 2J5",
    "country": "Canada",
    "phone": "(888) 212-5533",
    "website": "https://www.rbc.com",
    "industry": "Banks - Diversified",
    "industryKey": "banks-diversified",
    "industryDisp": "Banks - Diversified",
    "sector": "Financial Services",
    "sectorKey": "financial-services",
    "sectorDisp": "Financial Services",
    "longBusinessSummary": "Royal Bank of Canada operates as a diversified financial service company worldwide. Its Personal Banking segment offers home equity financing, personal lending, chequing and savings accounts, private banking, auto financing, mutual funds, GICs, credit cards, and payment products and solutions. The company's Commercial Banking segments provides lending, deposit and transaction banking products and services. Its Wealth Management segment provides a suite of wealth, investment, trust, banking, credit, and other solutions to clients; asset management products to institutional and individual clients; and asset and investor services to financial institutions, asset managers, and asset owners. The company's Insurance segment offers life, health, travel, wealth, annuities, property and casualty, and reinsurance advice and solutions; digital platforms; and independent brokers and partners, as well as client-led advice and solutions. The company's Capital Markets segment offers advisory and origination, sales and trading, lending and financing, and transaction banking services to corporations, institutional clients, asset managers, private equity firms, and governments. The company was founded in 1864 and is headquartered in Toronto, Canada.",
    "fullTimeEmployees": 97116,
    "companyOfficers": [
        {
            "maxAge": 1,
            "name": "Mr. David I. McKay",
            "age": 61,
            "title": "President, CEO & Director",
            "yearBorn": 1963,
            "fiscalYear": 2024,
            "totalPay": 8641626,
            "exercisedValue": 0,
            "unexercisedValue": 0
        },
        {
            "maxAge": 1,
            "name": "Ms. Katherine  Gibson",
            "title": "CFO & Controller",
            "fiscalYear": 2024,
            "totalPay": 1931794,
            "exercisedValue": 0,
            "unexercisedValue": 0
        },
        {
            "maxAge": 1,
            "name": "Mr. Douglas Antony Guzman",
            "age": 59,
            "title": "Deputy Chair",
            "yearBorn": 1965,
            "fiscalYear": 2024,
            "totalPay": 3387125,
            "exercisedValue": 0,
            "unexercisedValue": 0
        },
        {
            "maxAge": 1,
            "name": "Mr. Neil  McLaughlin",
            "title": "Group Head of RBC Wealth Management",
            "fiscalYear": 2024,
            "totalPay": 2212829,
            "exercisedValue": 0,
            "unexercisedValue": 0
        },
        {
            "maxAge": 1,
            "name": "Mr. Derek  Neldner CFA",
            "title": "Group Head & CEO of RBC Capital Markets",
            "fiscalYear": 2024,
            "totalPay": 4554500,
            "exercisedValue": 0,
            "unexercisedValue": 0
        },
        {
            "maxAge": 1,
            "name": "Mr. Bruce  Ross",
            "title": "Group Head of Technology & Operations",
            "fiscalYear": 2024,
            "totalPay": 1452329,
            "exercisedValue": 0,
            "unexercisedValue": 0
        },
        {
            "maxAge": 1,
            "name": "Mr. Matthew R. Stopnik",
            "title": "Head of Investment Banking",
            "fiscalYear": 2024,
            "exercisedValue": 0,
            "unexercisedValue": 0
        },
        {
            "maxAge": 1,
            "name": "Ms. Maria  Douvas",
            "title": "Chief Legal & Administrative Officer",
            "fiscalYear": 2024,
            "exercisedValue": 0,
            "unexercisedValue": 0
        },
        {
            "maxAge": 1,
            "name": "Mr. Asim  Imran",
            "title": "Senior VP & Head of Investor Relations",
            "fiscalYear": 2024,
            "exercisedValue": 0,
            "unexercisedValue": 0
        },
        {
            "maxAge": 1,
            "name": "Ms. Kelly  Bradley",
            "title": "Chief Human Resources Officer",
            "fiscalYear": 2024,
            "exercisedValue": 0,
            "unexercisedValue": 0
        }
    ],
    "auditRisk": 7,
    "boardRisk": 2,
    "compensationRisk": 6,
    "shareHolderRightsRisk": 4,
    "overallRisk": 4,
    "governanceEpochDate": 1756684800,
    "compensationAsOfEpochDate": 1735603200,
    "irWebsite": "http://www.rbc.com/investorrelations/index.html",
    "executiveTeam": [],
    "maxAge": 86400,
    "priceHint": 2,
    "previousClose": 200.82,
    "open": 200.25,
    "dayLow": 199.54,
    "dayHigh": 200.7,
    "regularMarketPreviousClose": 200.82,
    "regularMarketOpen": 200.25,
    "regularMarketDayLow": 199.54,
    "regularMarketDayHigh": 200.7,
    "dividendRate": 6.16,
    "dividendYield": 3.09,
    "exDividendDate": 1761523200,
    "payoutRatio": 0.44779998,
    "fiveYearAvgDividendYield": 3.71,
    "beta": 1.058,
    "trailingPE": 15.100605,
    "forwardPE": 15.8185425,
    "volume": 2879832,
    "regularMarketVolume": 2879832,
    "averageVolume": 3573609,
    "averageVolume10days": 2135390,
    "averageDailyVolume10Day": 2135390,
    "bid": 199.55,
    "ask": 199.72,
    "bidSize": 0,
    "askSize": 0,
    "marketCap": 281540198400,
    "fiftyTwoWeekLow": 151.25,
    "fiftyTwoWeekHigh": 204.6,
    "priceToSalesTrailing12Months": 4.6709285,
    "fiftyDayAverage": 187.1438,
    "twoHundredDayAverage": 174.55486,
    "trailingAnnualDividendRate": 5.92,
    "trailingAnnualDividendYield": 0.029479135,
    "currency": "CAD",
    "tradeable": false,
    "enterpriseValue": 266185248,
    "profitMargins": 0.31768999,
    "floatShares": 1403669467,
    "sharesOutstanding": 1410310016,
    "sharesShort": 4211831,
    "sharesShortPriorMonth": 5521223,
    "sharesShortPreviousMonthDate": 1753920000,
    "dateShortInterest": 1756771200,
    "sharesPercentSharesOut": 0.0047,
    "heldPercentInsiders": 0.0004,
    "heldPercentInstitutions": 0.49055,
    "shortRatio": 2.06,
    "impliedSharesOutstanding": 1410310016,
    "bookValue": 88.3,
    "priceToBook": 2.2608154,
    "lastFiscalYearEnd": 1730332800,
    "nextFiscalYearEnd": 1761868800,
    "mostRecentQuarter": 1753920000,
    "earningsQuarterlyGrowth": 0.208,
    "netIncomeToCommon": 18702999552,
    "trailingEps": 13.22,
    "forwardEps": 12.62,
    "lastSplitFactor": "2:1",
    "lastSplitDate": 1143072000,
    "enterpriseToRevenue": 0.004,
    "52WeekChange": 0.191252,
    "SandP52WeekChange": 0.16885936,
    "lastDividendValue": 1.54,
    "lastDividendDate": 1753315200,
    "quoteType": "EQUITY",
    "currentPrice": 199.63,
    "targetHighPrice": 227.0,
    "targetLowPrice": 169.0,
    "targetMeanPrice": 208.85715,
    "targetMedianPrice": 209.0,
    "recommendationMean": 1.8,
    "recommendationKey": "buy",
    "numberOfAnalystOpinions": 14,
    "totalCash": 730760019968,
    "totalCashPerShare": 520.118,
    "totalDebt": 438981001216,
    "totalRevenue": 60274999296,
    "revenuePerShare": 42.695,
    "returnOnAssets": 0.0089,
    "returnOnEquity": 0.14729,
    "grossProfits": 60274999296,
    "operatingCashflow": -33019000832,
    "earningsGrowth": 0.214,
    "revenueGrowth": 0.153,
    "grossMargins": 0.0,
    "ebitdaMargins": 0.0,
    "operatingMargins": 0.45380002,
    "financialCurrency": "CAD",
    "symbol": "RY.TO",
    "language": "en-US",
    "region": "US",
    "typeDisp": "Equity",
    "quoteSourceName": "Delayed Quote",
    "triggerable": true,
    "customPriceAlertConfidence": "HIGH",
    "corporateActions": [],
    "marketState": "CLOSED",
    "regularMarketPrice": 199.63,
    "exchange": "TOR",
    "messageBoardId": "finmb_109809",
    "exchangeTimezoneName": "America/Toronto",
    "exchangeTimezoneShortName": "EDT",
    "gmtOffSetMilliseconds": -14400000,
    "market": "ca_market",
    "esgPopulated": false,
    "shortName": "ROYAL BANK OF CANADA",
    "regularMarketChangePercent": -0.5925716,
    "cryptoTradeable": false,
    "longName": "Royal Bank of Canada",
    "regularMarketChange": -1.1900024,
    "regularMarketDayRange": "199.54 - 200.7",
    "fullExchangeName": "Toronto",
    "averageDailyVolume3Month": 3573609,
    "fiftyTwoWeekLowChange": 48.380005,
    "fiftyTwoWeekLowChangePercent": 0.3198678,
    "fiftyTwoWeekRange": "151.25 - 204.6",
    "fiftyTwoWeekHighChange": -4.970001,
    "fiftyTwoWeekHighChangePercent": -0.024291305,
    "fiftyTwoWeekChangePercent": 19.125198,
    "dividendDate": 1763942400,
    "earningsTimestamp": 1756297800,
    "earningsTimestampStart": 1756297800,
    "earningsTimestampEnd": 1756297800,
    "earningsCallTimestampStart": 1764768600,
    "earningsCallTimestampEnd": 1764768600,
    "isEarningsDateEstimate": false,
    "epsTrailingTwelveMonths": 13.22,
    "epsForward": 12.62,
    "epsCurrentYear": 14.03846,
    "priceEpsCurrentYear": 14.2202215,
    "fiftyDayAverageChange": 12.486206,
    "fiftyDayAverageChangePercent": 0.06671985,
    "hasPrePostMarketData": false,
    "firstTradeDateMilliseconds": 789921000000,
    "twoHundredDayAverageChange": 25.07515,
    "twoHundredDayAverageChangePercent": 0.14365198,
    "sourceInterval": 15,
    "exchangeDataDelayedBy": 15,
    "averageAnalystRating": "1.8 - Buy",
    "regularMarketTime": 1757707200,
    "trailingPegRatio": null
}